universal_ml_utils/__init__.py
universal_ml_utils/configuration.py
universal_ml_utils/io.py
universal_ml_utils/logging.py
universal_ml_utils/ops.py
universal_ml_utils/table.py
universal_ml_utils/decoding/__init__.py
universal_ml_utils/decoding/beam.py
universal_ml_utils/decoding/utils.py
universal_ml_utils-0.1.3.dist-info/licenses/LICENSE
universal_ml_utils-0.1.3.dist-info/METADATA
universal_ml_utils-0.1.3.dist-info/WHEEL
universal_ml_utils-0.1.3.dist-info/top_level.txt
universal_ml_utils-0.1.3.dist-info/RECORD
