Metadata-Version: 2.4
Name: universal-ml-utils
Version: 0.1.3
Summary: Collection of utilities for machine learning projects
Author-email: Sebastian Walter <swalter@cs.uni-freiburg.de>
License:                                  Apache License
Project-URL: Github, https://github.com/bastiscode/universal-ml-utils
Keywords: machine learning,utilities
Classifier: Programming Language :: Python :: 3
Classifier: Topic :: Scientific/Engineering :: Artificial Intelligence
Classifier: Topic :: Software Development :: Libraries
Classifier: Topic :: Utilities
Requires-Python: >=3.10
License-File: LICENSE
Requires-Dist: pyyaml>=6.0
Requires-Dist: termcolor>=2.4
Dynamic: license-file
